galamo/__init__.py
galamo/bpt.py
galamo/model.py
galamo/psr.py
galamo-1.1.2.dist-info/licenses/LICENSE
galamo-1.1.2.dist-info/METADATA
galamo-1.1.2.dist-info/WHEEL
galamo-1.1.2.dist-info/top_level.txt
galamo-1.1.2.dist-info/RECORD
