Metadata-Version: 2.4
Name: galamo
Version: 1.1.2
Summary: An open source Python package for comprehensive galaxy analysis, integrating machine learning and statistical methods. It provides automated tools for morphology classification, kinematics, photometry, and spectral analysis to aid astrophysical research.
Home-page: https://www.galamo.org
Author: Jashanpreet Singh Dingra
Author-email: astrodingra@gmail.com
Project-URL: Source Code, https://github.com/galamo-org/galamo
Project-URL: Documentation, https://galamo.org/docs
Project-URL: Bug Tracker, https://github.com/galamo-org/galamo/issues
Project-URL: Model Repository, https://huggingface.co/astrodingra/galamo
Classifier: Development Status :: 4 - Beta
Classifier: Intended Audience :: Science/Research
Classifier: License :: OSI Approved :: BSD License
Classifier: Programming Language :: Python :: 3
Classifier: Topic :: Scientific/Engineering :: Astronomy
Requires-Python: >=3.10
License-File: LICENSE
Requires-Dist: tensorflow>=2.10.0
Requires-Dist: numpy>=1.23.0
Requires-Dist: pandas>=1.5.0
Requires-Dist: scipy>=1.9.0
Requires-Dist: opencv-python>=4.6.0
Requires-Dist: joblib>=1.2.0
Requires-Dist: matplotlib>=3.6.0
Requires-Dist: termcolor>=2.0.0
Requires-Dist: requests>=2.28.0
Requires-Dist: huggingface_hub>=0.14.0
Requires-Dist: tqdm>=4.64.0
Dynamic: author
Dynamic: author-email
Dynamic: classifier
Dynamic: description
Dynamic: description-content-type
Dynamic: home-page
Dynamic: license-file
Dynamic: project-url
Dynamic: requires-dist
Dynamic: requires-python
Dynamic: summary
